{
  "users": {
    "7159434413": {
      "first_seen": "2026-05-05T20:27:00.424185",
      "platforms": [
        "telegram"
      ],
      "interactions_count": 10,
      "favorite_topics": [],
      "archetype": null,
      "cook_level": null,
      "respect_score": 0,
      "sentiment_history": [],
      "last_active": "2026-05-06T01:58:51.399978",
      "engagement_pattern": "unknown"
    },
    "7007869351": {
      "first_seen": "2026-05-05T20:34:11.097098",
      "platforms": [
        "telegram"
      ],
      "interactions_count": 14,
      "favorite_topics": [],
      "archetype": null,
      "cook_level": null,
      "respect_score": 0,
      "sentiment_history": [],
      "last_active": "2026-05-06T00:09:42.811409",
      "engagement_pattern": "unknown"
    },
    "7580022126": {
      "first_seen": "2026-05-05T20:43:16.164358",
      "platforms": [
        "telegram"
      ],
      "interactions_count": 1,
      "favorite_topics": [],
      "archetype": null,
      "cook_level": null,
      "respect_score": 0,
      "sentiment_history": [],
      "last_active": "2026-05-05T20:43:16.164375",
      "engagement_pattern": "unknown"
    },
    "1087968824": {
      "first_seen": "2026-05-05T20:50:30.223508",
      "platforms": [
        "telegram"
      ],
      "interactions_count": 43,
      "favorite_topics": [],
      "archetype": null,
      "cook_level": null,
      "respect_score": 0,
      "sentiment_history": [],
      "last_active": "2026-05-06T02:10:10.266199",
      "engagement_pattern": "unknown"
    },
    "8460260157": {
      "first_seen": "2026-05-05T20:52:51.329883",
      "platforms": [
        "telegram"
      ],
      "interactions_count": 2,
      "favorite_topics": [],
      "archetype": null,
      "cook_level": null,
      "respect_score": 0,
      "sentiment_history": [],
      "last_active": "2026-05-05T20:54:23.949734",
      "engagement_pattern": "unknown"
    },
    "5687037912": {
      "first_seen": "2026-05-05T21:11:57.046445",
      "platforms": [
        "telegram"
      ],
      "interactions_count": 1,
      "favorite_topics": [],
      "archetype": null,
      "cook_level": null,
      "respect_score": 0,
      "sentiment_history": [],
      "last_active": "2026-05-05T21:11:57.046477",
      "engagement_pattern": "unknown"
    },
    "7697478733": {
      "first_seen": "2026-05-05T21:22:41.570049",
      "platforms": [
        "telegram"
      ],
      "interactions_count": 3,
      "favorite_topics": [],
      "archetype": null,
      "cook_level": null,
      "respect_score": 0,
      "sentiment_history": [],
      "last_active": "2026-05-06T02:06:12.568940",
      "engagement_pattern": "unknown"
    },
    "8292209775": {
      "first_seen": "2026-05-05T23:23:41.846942",
      "platforms": [
        "telegram"
      ],
      "interactions_count": 2,
      "favorite_topics": [],
      "archetype": null,
      "cook_level": null,
      "respect_score": 0,
      "sentiment_history": [],
      "last_active": "2026-05-05T23:27:16.596205",
      "engagement_pattern": "unknown"
    },
    "5202445066": {
      "first_seen": "2026-05-06T00:10:15.828996",
      "platforms": [
        "telegram"
      ],
      "interactions_count": 1,
      "favorite_topics": [],
      "archetype": null,
      "cook_level": null,
      "respect_score": 0,
      "sentiment_history": [],
      "last_active": "2026-05-06T00:10:15.829013",
      "engagement_pattern": "unknown"
    },
    "7598354099": {
      "first_seen": "2026-05-06T01:17:58.911486",
      "platforms": [
        "telegram"
      ],
      "interactions_count": 16,
      "favorite_topics": [],
      "archetype": null,
      "cook_level": null,
      "respect_score": 0,
      "sentiment_history": [],
      "last_active": "2026-05-06T02:05:56.057723",
      "engagement_pattern": "unknown"
    },
    "6844734734": {
      "first_seen": "2026-05-06T02:06:56.144328",
      "platforms": [
        "telegram"
      ],
      "interactions_count": 1,
      "favorite_topics": [],
      "archetype": null,
      "cook_level": null,
      "respect_score": 0,
      "sentiment_history": [],
      "last_active": "2026-05-06T02:06:56.144344",
      "engagement_pattern": "unknown"
    },
    "5571662239": {
      "first_seen": "2026-05-06T02:09:10.093380",
      "platforms": [
        "telegram"
      ],
      "interactions_count": 2,
      "favorite_topics": [],
      "archetype": null,
      "cook_level": null,
      "respect_score": 0,
      "sentiment_history": [],
      "last_active": "2026-05-06T02:09:53.951029",
      "engagement_pattern": "unknown"
    }
  },
  "interactions": [
    {
      "user_id": "7159434413",
      "platform": "telegram",
      "action": "message",
      "content": "Can someone make me mad",
      "sentiment": null,
      "timestamp": "2026-05-05T20:27:00.424196",
      "metadata": {}
    },
    {
      "user_id": "7159434413",
      "platform": "telegram",
      "action": "message",
      "content": "Mad house 😡",
      "sentiment": null,
      "timestamp": "2026-05-05T20:33:55.066572",
      "metadata": {}
    },
    {
      "user_id": "7007869351",
      "platform": "telegram",
      "action": "message",
      "content": "Yeah, where Mad love is shared 😡💪",
      "sentiment": null,
      "timestamp": "2026-05-05T20:34:11.097120",
      "metadata": {}
    },
    {
      "user_id": "7580022126",
      "platform": "telegram",
      "action": "message",
      "content": "😡",
      "sentiment": null,
      "timestamp": "2026-05-05T20:43:16.164380",
      "metadata": {}
    },
    {
      "user_id": "1087968824",
      "platform": "telegram",
      "action": "message",
      "content": "Moltbook",
      "sentiment": null,
      "timestamp": "2026-05-05T20:50:30.223528",
      "metadata": {}
    },
    {
      "user_id": "8460260157",
      "platform": "telegram",
      "action": "message",
      "content": "lets smash more post every one",
      "sentiment": null,
      "timestamp": "2026-05-05T20:52:51.329903",
      "metadata": {}
    },
    {
      "user_id": "8460260157",
      "platform": "telegram",
      "action": "message",
      "content": "https://x.com/deenygigi/status/2051745574370640175?s=46",
      "sentiment": null,
      "timestamp": "2026-05-05T20:54:23.949754",
      "metadata": {}
    },
    {
      "user_id": "5687037912",
      "platform": "telegram",
      "action": "message",
      "content": "we're still early",
      "sentiment": null,
      "timestamp": "2026-05-05T21:11:57.046483",
      "metadata": {}
    },
    {
      "user_id": "7697478733",
      "platform": "telegram",
      "action": "message",
      "content": "So early",
      "sentiment": null,
      "timestamp": "2026-05-05T21:22:41.570069",
      "metadata": {}
    },
    {
      "user_id": "7007869351",
      "platform": "telegram",
      "action": "message",
      "content": "$MAD EARLY 😡",
      "sentiment": null,
      "timestamp": "2026-05-05T21:23:02.069135",
      "metadata": {}
    },
    {
      "user_id": "7007869351",
      "platform": "telegram",
      "action": "message",
      "content": "Mad Hyped Chad 😡",
      "sentiment": null,
      "timestamp": "2026-05-05T21:38:09.261005",
      "metadata": {}
    },
    {
      "user_id": "1087968824",
      "platform": "telegram",
      "action": "message",
      "content": "https://x.com/madrichclub_/status/2051788224968941854?s=46",
      "sentiment": null,
      "timestamp": "2026-05-05T22:17:07.220470",
      "metadata": {}
    },
    {
      "user_id": "7007869351",
      "platform": "telegram",
      "action": "message",
      "content": "Smash up fam 👊🏽",
      "sentiment": null,
      "timestamp": "2026-05-05T22:59:29.094464",
      "metadata": {}
    },
    {
      "user_id": "7007869351",
      "platform": "telegram",
      "action": "message",
      "content": "Fuck!",
      "sentiment": null,
      "timestamp": "2026-05-05T23:23:17.492028",
      "metadata": {}
    },
    {
      "user_id": "7007869351",
      "platform": "telegram",
      "action": "message",
      "content": "We almost smashed it😡",
      "sentiment": null,
      "timestamp": "2026-05-05T23:23:25.463484",
      "metadata": {}
    },
    {
      "user_id": "7007869351",
      "platform": "telegram",
      "action": "message",
      "content": "https://x.com/madrichclub_/status/2051788224968941854",
      "sentiment": null,
      "timestamp": "2026-05-05T23:23:37.946663",
      "metadata": {}
    },
    {
      "user_id": "8292209775",
      "platform": "telegram",
      "action": "message",
      "content": "We are all $MAD",
      "sentiment": null,
      "timestamp": "2026-05-05T23:23:41.846962",
      "metadata": {}
    },
    {
      "user_id": "7007869351",
      "platform": "telegram",
      "action": "message",
      "content": "Yeah we are Mad blessed",
      "sentiment": null,
      "timestamp": "2026-05-05T23:25:04.413929",
      "metadata": {}
    },
    {
      "user_id": "8292209775",
      "platform": "telegram",
      "action": "message",
      "content": "Fr",
      "sentiment": null,
      "timestamp": "2026-05-05T23:27:16.596220",
      "metadata": {}
    },
    {
      "user_id": "7007869351",
      "platform": "telegram",
      "action": "message",
      "content": "Is that Rolex on your wrist 👀",
      "sentiment": null,
      "timestamp": "2026-05-05T23:32:58.261546",
      "metadata": {}
    },
    {
      "user_id": "1087968824",
      "platform": "telegram",
      "action": "message",
      "content": "Just finished a MAD MEETING 😡 lots cooking 👀",
      "sentiment": null,
      "timestamp": "2026-05-05T23:44:56.705037",
      "metadata": {}
    },
    {
      "user_id": "1087968824",
      "platform": "telegram",
      "action": "message",
      "content": "No just a Gucci watch",
      "sentiment": null,
      "timestamp": "2026-05-05T23:45:07.560443",
      "metadata": {}
    },
    {
      "user_id": "7007869351",
      "platform": "telegram",
      "action": "message",
      "content": "Must be a classic one for Mad rich dev 🔥😡",
      "sentiment": null,
      "timestamp": "2026-05-05T23:47:01.883704",
      "metadata": {}
    },
    {
      "user_id": "7007869351",
      "platform": "telegram",
      "action": "message",
      "content": "Amazing 🔥🔥🔥🔥.... More madness for faders 🔥😡",
      "sentiment": null,
      "timestamp": "2026-05-05T23:47:56.210867",
      "metadata": {}
    },
    {
      "user_id": "1087968824",
      "platform": "telegram",
      "action": "message",
      "content": "Honestly I would feel uncomfortable walking around with a down payment on a house on my wrist 🤣",
      "sentiment": null,
      "timestamp": "2026-05-06T00:00:15.561773",
      "metadata": {}
    },
    {
      "user_id": "7007869351",
      "platform": "telegram",
      "action": "message",
      "content": "Alright then 😁😡",
      "sentiment": null,
      "timestamp": "2026-05-06T00:05:16.179916",
      "metadata": {}
    },
    {
      "user_id": "7007869351",
      "platform": "telegram",
      "action": "message",
      "content": "Instead you use it to stack some cards",
      "sentiment": null,
      "timestamp": "2026-05-06T00:05:34.200009",
      "metadata": {}
    },
    {
      "user_id": "1087968824",
      "platform": "telegram",
      "action": "message",
      "content": "i mean the most important thing to understand is who is the next fool that will buy 200k watch not many buyers",
      "sentiment": null,
      "timestamp": "2026-05-06T00:06:10.368440",
      "metadata": {}
    },
    {
      "user_id": "1087968824",
      "platform": "telegram",
      "action": "message",
      "content": "thats something you really have to think about when it comes to money",
      "sentiment": null,
      "timestamp": "2026-05-06T00:06:23.353366",
      "metadata": {}
    },
    {
      "user_id": "1087968824",
      "platform": "telegram",
      "action": "message",
      "content": "and a lot of people i know feel uncomfortable too with the amount of theft going on",
      "sentiment": null,
      "timestamp": "2026-05-06T00:06:50.971358",
      "metadata": {}
    },
    {
      "user_id": "1087968824",
      "platform": "telegram",
      "action": "message",
      "content": "like i bet if you bought 1 and wore it around your city you would feel mad uncomfortable",
      "sentiment": null,
      "timestamp": "2026-05-06T00:07:14.570884",
      "metadata": {}
    },
    {
      "user_id": "1087968824",
      "platform": "telegram",
      "action": "message",
      "content": "Posted on the MAD Insta 😡🔥🤝",
      "sentiment": null,
      "timestamp": "2026-05-06T00:09:19.766903",
      "metadata": {}
    },
    {
      "user_id": "1087968824",
      "platform": "telegram",
      "action": "message",
      "content": "Instagram",
      "sentiment": null,
      "timestamp": "2026-05-06T00:09:28.520685",
      "metadata": {}
    },
    {
      "user_id": "7007869351",
      "platform": "telegram",
      "action": "message",
      "content": "Active 😁😡",
      "sentiment": null,
      "timestamp": "2026-05-06T00:09:42.811426",
      "metadata": {}
    },
    {
      "user_id": "5202445066",
      "platform": "telegram",
      "action": "message",
      "content": "I don’t like fake vibes, and yeah something to be $MAD about!",
      "sentiment": null,
      "timestamp": "2026-05-06T00:10:15.829019",
      "metadata": {}
    },
    {
      "user_id": "1087968824",
      "platform": "telegram",
      "action": "message",
      "content": "last raid for the day https://x.com/madrichclub_/status/2051830589876257104?s=20",
      "sentiment": null,
      "timestamp": "2026-05-06T01:05:20.290195",
      "metadata": {}
    },
    {
      "user_id": "1087968824",
      "platform": "telegram",
      "action": "message",
      "content": "LFG!",
      "sentiment": null,
      "timestamp": "2026-05-06T01:07:18.213187",
      "metadata": {}
    },
    {
      "user_id": "1087968824",
      "platform": "telegram",
      "action": "message",
      "content": "WE $MAD FAM THE BEST COMMUNITY!!!!!!",
      "sentiment": null,
      "timestamp": "2026-05-06T01:07:43.726755",
      "metadata": {}
    },
    {
      "user_id": "7159434413",
      "platform": "telegram",
      "action": "message",
      "content": "THE MAD HOUSE",
      "sentiment": null,
      "timestamp": "2026-05-06T01:08:06.577497",
      "metadata": {}
    },
    {
      "user_id": "7159434413",
      "platform": "telegram",
      "action": "message",
      "content": "You can say that again best mad dev ever",
      "sentiment": null,
      "timestamp": "2026-05-06T01:08:46.879996",
      "metadata": {}
    },
    {
      "user_id": "1087968824",
      "platform": "telegram",
      "action": "message",
      "content": "together we RISE and show why we are MAD 😡",
      "sentiment": null,
      "timestamp": "2026-05-06T01:09:37.174547",
      "metadata": {}
    },
    {
      "user_id": "7159434413",
      "platform": "telegram",
      "action": "message",
      "content": "Today is my birthday I really need to get to the mad club 😡",
      "sentiment": null,
      "timestamp": "2026-05-06T01:10:07.311203",
      "metadata": {}
    },
    {
      "user_id": "7159434413",
      "platform": "telegram",
      "action": "message",
      "content": "Good vibes only because the mad dev has giving us all we want so why will I leave the mad house 🤷",
      "sentiment": null,
      "timestamp": "2026-05-06T01:12:07.936902",
      "metadata": {}
    },
    {
      "user_id": "1087968824",
      "platform": "telegram",
      "action": "message",
      "content": "HAPPY MAD BIRTHDAY WHAT! 😡🔥",
      "sentiment": null,
      "timestamp": "2026-05-06T01:12:13.248281",
      "metadata": {}
    },
    {
      "user_id": "7159434413",
      "platform": "telegram",
      "action": "message",
      "content": "Thank you sir",
      "sentiment": null,
      "timestamp": "2026-05-06T01:12:35.164668",
      "metadata": {}
    },
    {
      "user_id": "1087968824",
      "platform": "telegram",
      "action": "message",
      "content": "LFG! 😡🤝🔥",
      "sentiment": null,
      "timestamp": "2026-05-06T01:17:33.588815",
      "metadata": {}
    },
    {
      "user_id": "7159434413",
      "platform": "telegram",
      "action": "message",
      "content": "Let’s keep supporting the community guys",
      "sentiment": null,
      "timestamp": "2026-05-06T01:17:50.488524",
      "metadata": {}
    },
    {
      "user_id": "7159434413",
      "platform": "telegram",
      "action": "message",
      "content": "We are the future 😡",
      "sentiment": null,
      "timestamp": "2026-05-06T01:17:56.190787",
      "metadata": {}
    },
    {
      "user_id": "7598354099",
      "platform": "telegram",
      "action": "message",
      "content": "I spy, with my little eye, a chad who knows something ... 👀",
      "sentiment": null,
      "timestamp": "2026-05-06T01:17:58.911507",
      "metadata": {}
    },
    {
      "user_id": "1087968824",
      "platform": "telegram",
      "action": "message",
      "content": "he a MAD man but also not surprised",
      "sentiment": null,
      "timestamp": "2026-05-06T01:18:42.305598",
      "metadata": {}
    },
    {
      "user_id": "7598354099",
      "platform": "telegram",
      "action": "message",
      "content": "I have a feeling lots of people are gonna be upset to have missed the train",
      "sentiment": null,
      "timestamp": "2026-05-06T01:19:41.121997",
      "metadata": {}
    },
    {
      "user_id": "7598354099",
      "platform": "telegram",
      "action": "message",
      "content": "Is there a KOL marketing plan in the cards down the road?",
      "sentiment": null,
      "timestamp": "2026-05-06T01:19:57.682184",
      "metadata": {}
    },
    {
      "user_id": "7598354099",
      "platform": "telegram",
      "action": "message",
      "content": "Or all organic?",
      "sentiment": null,
      "timestamp": "2026-05-06T01:20:01.981689",
      "metadata": {}
    },
    {
      "user_id": "1087968824",
      "platform": "telegram",
      "action": "message",
      "content": "organic",
      "sentiment": null,
      "timestamp": "2026-05-06T01:20:09.988411",
      "metadata": {}
    },
    {
      "user_id": "1087968824",
      "platform": "telegram",
      "action": "message",
      "content": "good they can stay MAD",
      "sentiment": null,
      "timestamp": "2026-05-06T01:20:23.584988",
      "metadata": {}
    },
    {
      "user_id": "1087968824",
      "platform": "telegram",
      "action": "message",
      "content": "and FUCK THOSE KOLS MAN they going to DUMP ON YOUR ASS",
      "sentiment": null,
      "timestamp": "2026-05-06T01:20:34.044508",
      "metadata": {}
    },
    {
      "user_id": "1087968824",
      "platform": "telegram",
      "action": "message",
      "content": "they can buy higher and on top of your bags",
      "sentiment": null,
      "timestamp": "2026-05-06T01:20:45.067545",
      "metadata": {}
    },
    {
      "user_id": "1087968824",
      "platform": "telegram",
      "action": "message",
      "content": "themadclaw",
      "sentiment": null,
      "timestamp": "2026-05-06T01:54:47.110804",
      "metadata": {}
    },
    {
      "user_id": "7159434413",
      "platform": "telegram",
      "action": "message",
      "content": "Big mad man",
      "sentiment": null,
      "timestamp": "2026-05-06T01:58:51.399995",
      "metadata": {}
    },
    {
      "user_id": "7598354099",
      "platform": "telegram",
      "action": "message",
      "content": "Okay, so consider this my retarded question of the day",
      "sentiment": null,
      "timestamp": "2026-05-06T02:00:59.210796",
      "metadata": {}
    },
    {
      "user_id": "1087968824",
      "platform": "telegram",
      "action": "message",
      "content": "i love the way you said this",
      "sentiment": null,
      "timestamp": "2026-05-06T02:01:12.758181",
      "metadata": {}
    },
    {
      "user_id": "7598354099",
      "platform": "telegram",
      "action": "message",
      "content": "But the burns help push the MC up, right?",
      "sentiment": null,
      "timestamp": "2026-05-06T02:01:14.652384",
      "metadata": {}
    },
    {
      "user_id": "1087968824",
      "platform": "telegram",
      "action": "message",
      "content": "yes exponentially",
      "sentiment": null,
      "timestamp": "2026-05-06T02:01:28.498417",
      "metadata": {}
    },
    {
      "user_id": "1087968824",
      "platform": "telegram",
      "action": "message",
      "content": "let me show you the real market cap",
      "sentiment": null,
      "timestamp": "2026-05-06T02:01:35.214912",
      "metadata": {}
    },
    {
      "user_id": "7598354099",
      "platform": "telegram",
      "action": "message",
      "content": "Like, I just saw the MC jump from 160k to 164k on Dex",
      "sentiment": null,
      "timestamp": "2026-05-06T02:01:35.959594",
      "metadata": {}
    },
    {
      "user_id": "1087968824",
      "platform": "telegram",
      "action": "message",
      "content": "this is the real marketcap",
      "sentiment": null,
      "timestamp": "2026-05-06T02:01:48.728874",
      "metadata": {}
    },
    {
      "user_id": "7598354099",
      "platform": "telegram",
      "action": "message",
      "content": "But the only new TX was a $5 and $10 buy",
      "sentiment": null,
      "timestamp": "2026-05-06T02:02:01.979617",
      "metadata": {}
    },
    {
      "user_id": "7598354099",
      "platform": "telegram",
      "action": "message",
      "content": "But you did just do a burn too, so assuming that helped?",
      "sentiment": null,
      "timestamp": "2026-05-06T02:02:20.764012",
      "metadata": {}
    },
    {
      "user_id": "1087968824",
      "platform": "telegram",
      "action": "message",
      "content": "so when people buy now it jumps MAD fast because not a lot of supply",
      "sentiment": null,
      "timestamp": "2026-05-06T02:02:21.029147",
      "metadata": {}
    },
    {
      "user_id": "1087968824",
      "platform": "telegram",
      "action": "message",
      "content": "so as soon as we touch 500k market cap shown on dex technically we are at 1m which will trigger many signals in the trenches",
      "sentiment": null,
      "timestamp": "2026-05-06T02:02:50.615420",
      "metadata": {}
    },
    {
      "user_id": "7598354099",
      "platform": "telegram",
      "action": "message",
      "content": "Wait ... $326k?!?!",
      "sentiment": null,
      "timestamp": "2026-05-06T02:02:53.151856",
      "metadata": {}
    },
    {
      "user_id": "7598354099",
      "platform": "telegram",
      "action": "message",
      "content": "How and where?!",
      "sentiment": null,
      "timestamp": "2026-05-06T02:02:55.823036",
      "metadata": {}
    },
    {
      "user_id": "1087968824",
      "platform": "telegram",
      "action": "message",
      "content": "on pumpfun",
      "sentiment": null,
      "timestamp": "2026-05-06T02:03:02.526757",
      "metadata": {}
    },
    {
      "user_id": "7598354099",
      "platform": "telegram",
      "action": "message",
      "content": "I only see on Dex",
      "sentiment": null,
      "timestamp": "2026-05-06T02:03:03.074735",
      "metadata": {}
    },
    {
      "user_id": "1087968824",
      "platform": "telegram",
      "action": "message",
      "content": "the reason is because half of the supply is gone",
      "sentiment": null,
      "timestamp": "2026-05-06T02:03:24.540039",
      "metadata": {}
    },
    {
      "user_id": "1087968824",
      "platform": "telegram",
      "action": "message",
      "content": "so its an automatic 2x for anyones bags that has been holding",
      "sentiment": null,
      "timestamp": "2026-05-06T02:03:39.436871",
      "metadata": {}
    },
    {
      "user_id": "1087968824",
      "platform": "telegram",
      "action": "message",
      "content": "so currently if we touch 500M market cap technically we are worth 1B which = to $1",
      "sentiment": null,
      "timestamp": "2026-05-06T02:04:00.081163",
      "metadata": {}
    },
    {
      "user_id": "7598354099",
      "platform": "telegram",
      "action": "message",
      "content": "Hfs",
      "sentiment": null,
      "timestamp": "2026-05-06T02:04:39.050356",
      "metadata": {}
    },
    {
      "user_id": "1087968824",
      "platform": "telegram",
      "action": "message",
      "content": "hfs?",
      "sentiment": null,
      "timestamp": "2026-05-06T02:04:47.801707",
      "metadata": {}
    },
    {
      "user_id": "7598354099",
      "platform": "telegram",
      "action": "message",
      "content": "Holy Fvcking Sh*t",
      "sentiment": null,
      "timestamp": "2026-05-06T02:05:05.988840",
      "metadata": {}
    },
    {
      "user_id": "7697478733",
      "platform": "telegram",
      "action": "message",
      "content": "Holly fucking shit",
      "sentiment": null,
      "timestamp": "2026-05-06T02:05:07.965519",
      "metadata": {}
    },
    {
      "user_id": "1087968824",
      "platform": "telegram",
      "action": "message",
      "content": "oh lol XD",
      "sentiment": null,
      "timestamp": "2026-05-06T02:05:13.252813",
      "metadata": {}
    },
    {
      "user_id": "7598354099",
      "platform": "telegram",
      "action": "message",
      "content": "Oh I know the supply side of the equation, but curious why Dex isnt reflecting what Pump is?",
      "sentiment": null,
      "timestamp": "2026-05-06T02:05:35.231155",
      "metadata": {}
    },
    {
      "user_id": "1087968824",
      "platform": "telegram",
      "action": "message",
      "content": "yeah so we're going to fly real fast with supply shock when people actually discover whats going on",
      "sentiment": null,
      "timestamp": "2026-05-06T02:05:41.007515",
      "metadata": {}
    },
    {
      "user_id": "1087968824",
      "platform": "telegram",
      "action": "message",
      "content": "idk but i like it good for the MAD narrative",
      "sentiment": null,
      "timestamp": "2026-05-06T02:05:55.675860",
      "metadata": {}
    },
    {
      "user_id": "7598354099",
      "platform": "telegram",
      "action": "message",
      "content": "Are there more holders on Pump that arent captured on Dex too?",
      "sentiment": null,
      "timestamp": "2026-05-06T02:05:56.057762",
      "metadata": {}
    },
    {
      "user_id": "7697478733",
      "platform": "telegram",
      "action": "message",
      "content": "No",
      "sentiment": null,
      "timestamp": "2026-05-06T02:06:12.568967",
      "metadata": {}
    },
    {
      "user_id": "6844734734",
      "platform": "telegram",
      "action": "message",
      "content": "gn",
      "sentiment": null,
      "timestamp": "2026-05-06T02:06:56.144351",
      "metadata": {}
    },
    {
      "user_id": "1087968824",
      "platform": "telegram",
      "action": "message",
      "content": "sleep well MAD bro",
      "sentiment": null,
      "timestamp": "2026-05-06T02:07:12.522568",
      "metadata": {}
    },
    {
      "user_id": "1087968824",
      "platform": "telegram",
      "action": "message",
      "content": "so when we touch 500M tokens in current supply im going to give 10k holders a chance to buy in before continuing to burn down to only there being 200M token in circulation",
      "sentiment": null,
      "timestamp": "2026-05-06T02:08:11.186356",
      "metadata": {}
    },
    {
      "user_id": "1087968824",
      "platform": "telegram",
      "action": "message",
      "content": "LFG!!!! yeah i saw you got that light aura on",
      "sentiment": null,
      "timestamp": "2026-05-06T02:08:45.898536",
      "metadata": {}
    },
    {
      "user_id": "5571662239",
      "platform": "telegram",
      "action": "message",
      "content": "Looks good on me,",
      "sentiment": null,
      "timestamp": "2026-05-06T02:09:10.093400",
      "metadata": {}
    },
    {
      "user_id": "1087968824",
      "platform": "telegram",
      "action": "message",
      "content": "that sword is sick too ngl!",
      "sentiment": null,
      "timestamp": "2026-05-06T02:09:26.372330",
      "metadata": {}
    },
    {
      "user_id": "5571662239",
      "platform": "telegram",
      "action": "message",
      "content": "Yep",
      "sentiment": null,
      "timestamp": "2026-05-06T02:09:53.951047",
      "metadata": {}
    },
    {
      "user_id": "1087968824",
      "platform": "telegram",
      "action": "message",
      "content": "i think the bot is autistic like my cat",
      "sentiment": null,
      "timestamp": "2026-05-06T02:10:04.985126",
      "metadata": {}
    },
    {
      "user_id": "1087968824",
      "platform": "telegram",
      "action": "message",
      "content": "AHAHA",
      "sentiment": null,
      "timestamp": "2026-05-06T02:10:10.266215",
      "metadata": {}
    }
  ],
  "topics": {
    "someone": 1,
    "make": 1,
    "house": 4,
    "where": 1,
    "love": 2,
    "shared": 1,
    "moltbook": 1,
    "lets": 1,
    "smash": 2,
    "more": 3,
    "post": 1,
    "every": 1,
    "still": 1,
    "early": 3,
    "hyped": 1,
    "chad": 2,
    "almost": 1,
    "smashed": 1,
    "yeah": 4,
    "blessed": 1,
    "that": 8,
    "rolex": 1,
    "your": 4,
    "wrist": 2,
    "just": 4,
    "finished": 1,
    "meeting": 1,
    "lots": 2,
    "cooking": 1,
    "gucci": 1,
    "watch": 2,
    "must": 1,
    "classic": 1,
    "rich": 1,
    "amazing": 1,
    "madness": 1,
    "faders": 1,
    "honestly": 1,
    "would": 2,
    "feel": 3,
    "uncomfortable": 3,
    "walking": 1,
    "around": 2,
    "with": 4,
    "down": 3,
    "payment": 1,
    "alright": 1,
    "then": 1,
    "instead": 1,
    "stack": 1,
    "some": 1,
    "cards": 2,
    "mean": 1,
    "most": 1,
    "important": 1,
    "thing": 1,
    "understand": 1,
    "next": 1,
    "fool": 1,
    "will": 3,
    "many": 2,
    "buyers": 1,
    "thats": 1,
    "something": 3,
    "really": 2,
    "have": 3,
    "think": 2,
    "about": 1,
    "when": 4,
    "comes": 1,
    "money": 1,
    "people": 4,
    "know": 2,
    "amount": 1,
    "theft": 1,
    "going": 5,
    "like": 4,
    "bought": 1,
    "wore": 1,
    "city": 1,
    "posted": 1,
    "insta": 1,
    "instagram": 1,
    "active": 1,
    "fake": 1,
    "last": 1,
    "raid": 1,
    "best": 2,
    "again": 1,
    "ever": 1,
    "together": 1,
    "rise": 1,
    "show": 2,
    "today": 1,
    "birthday": 2,
    "need": 1,
    "club": 1,
    "good": 4,
    "vibes": 1,
    "only": 4,
    "because": 3,
    "giving": 1,
    "want": 1,
    "leave": 1,
    "happy": 1,
    "thank": 1,
    "keep": 1,
    "supporting": 1,
    "community": 1,
    "guys": 1,
    "future": 1,
    "little": 1,
    "knows": 1,
    "also": 1,
    "surprised": 1,
    "feeling": 1,
    "gonna": 1,
    "upset": 1,
    "missed": 1,
    "train": 1,
    "there": 3,
    "marketing": 1,
    "plan": 1,
    "organic": 1,
    "they": 3,
    "stay": 1,
    "fuck": 1,
    "those": 1,
    "kols": 1,
    "dump": 1,
    "higher": 1,
    "bags": 2,
    "themadclaw": 1,
    "consider": 1,
    "this": 3,
    "retarded": 1,
    "question": 1,
    "said": 1,
    "burns": 1,
    "help": 1,
    "push": 1,
    "exponentially": 1,
    "real": 3,
    "market": 3,
    "jump": 1,
    "from": 1,
    "marketcap": 1,
    "burn": 2,
    "assuming": 1,
    "jumps": 1,
    "fast": 2,
    "supply": 5,
    "soon": 1,
    "touch": 3,
    "shown": 1,
    "technically": 2,
    "which": 2,
    "trigger": 1,
    "signals": 1,
    "trenches": 1,
    "wait": 1,
    "pumpfun": 1,
    "reason": 1,
    "half": 1,
    "gone": 1,
    "automatic": 1,
    "anyones": 1,
    "been": 1,
    "holding": 1,
    "currently": 1,
    "worth": 1,
    "holy": 1,
    "fvcking": 1,
    "holly": 1,
    "fucking": 1,
    "shit": 1,
    "side": 1,
    "curious": 1,
    "isnt": 1,
    "reflecting": 1,
    "what": 1,
    "pump": 2,
    "shock": 1,
    "actually": 1,
    "discover": 1,
    "whats": 1,
    "narrative": 1,
    "holders": 2,
    "arent": 1,
    "captured": 1,
    "sleep": 1,
    "well": 1,
    "tokens": 1,
    "current": 1,
    "give": 1,
    "chance": 1,
    "before": 1,
    "continuing": 1,
    "being": 1,
    "token": 1,
    "circulation": 1,
    "light": 1,
    "aura": 1,
    "looks": 1,
    "sword": 1,
    "sick": 1,
    "autistic": 1,
    "ahaha": 1
  },
  "phrases": {},
  "trends": [],
  "archetype_patterns": {},
  "roast_effectiveness": {},
  "daily_summaries": [],
  "created_at": "2026-05-05T20:27:00.424168"
}